AppleAPI/__init__.py
AppleAPI/apple_api_agent.py
AppleAPI/appstore.py
AppleAPI/models.py
appleapi-1.0.10.dist-info/licenses/LICENSE
appleapi-1.0.10.dist-info/METADATA
appleapi-1.0.10.dist-info/WHEEL
appleapi-1.0.10.dist-info/top_level.txt
appleapi-1.0.10.dist-info/RECORD
