Metadata-Version: 2.4
Name: AppleAPI
Version: 1.0.10
Summary: App Store Connect API
Home-page: https://github.com/yingguqing/AppleAPI
Author: 影孤清
Author-email: yingguqing@163.com
Keywords: ios apple appstore app store connect api appstoreconnectapi
Classifier: Development Status :: 5 - Production/Stable
Classifier: License :: OSI Approved :: MIT License
Classifier: Operating System :: POSIX
Classifier: Topic :: Software Development :: Libraries :: Python Modules
Classifier: Programming Language :: Python :: 3.7
Classifier: Programming Language :: Python :: 3.8
Classifier: Programming Language :: Python :: 3.9
Requires-Python: ~=3.7
License-File: LICENSE
Requires-Dist: PyJWT~=2.0
Requires-Dist: pyOpenSSL<=24.1.0,>=20.0.0
Requires-Dist: requests~=2.20
Dynamic: author
Dynamic: author-email
Dynamic: classifier
Dynamic: description
Dynamic: description-content-type
Dynamic: home-page
Dynamic: keywords
Dynamic: license-file
Dynamic: requires-dist
Dynamic: requires-python
Dynamic: summary
